pytracertool/__init__.py
pytracertool/pytracertool.py
pytracertool-2.0.4.dist-info/LICENSE
pytracertool-2.0.4.dist-info/METADATA
pytracertool-2.0.4.dist-info/WHEEL
pytracertool-2.0.4.dist-info/top_level.txt
pytracertool-2.0.4.dist-info/RECORD
