Metadata-Version: 2.1
Name: pytracertool
Version: 2.0.4
Summary: A versatile tool for tracing code execution, capturing variable changes, and logging print statements.
Home-page: https://github.com/DarshanLakshman/PyTracerTool.git
Author: Darshan Lakshman
Author-email: darshan.lakshman@icloud.com
Keywords: trace,debugging,tracing,execution,visualisation
Classifier: Development Status :: 4 - Beta
Classifier: Intended Audience :: Developers
Classifier: License :: OSI Approved :: MIT License
Classifier: Programming Language :: Python :: 3
Classifier: Operating System :: OS Independent
License-File: LICENSE
Requires-Dist: tabulate
Requires-Dist: typing
